README.md
setup.cfg
setup.py
distributions/Binomialdistribution.py
distributions/Gaussiandistribution.py
distributions/Generaldistribution.py
distributions/__init__.py
fares_distributions.egg-info/PKG-INFO
fares_distributions.egg-info/SOURCES.txt
fares_distributions.egg-info/dependency_links.txt
fares_distributions.egg-info/not-zip-safe
fares_distributions.egg-info/top_level.txt