Metadata-Version: 1.0
Name: fares-distributions
Version: 0.1
Summary: Gaussian distributions
Home-page: UNKNOWN
Author: Fares
Author-email: gdourafares@gmail.com
License: UNKNOWN
Platform: UNKNOWN
